CONTRIBUTING.md
LICENSE.md
README-DEV.md
README.md
requirements.txt
knapsack_problem/__init__.py
knapsack_problem/data.py
knapsack_problem/funcs.py
knapsack_problem/funcs.py.lprof
knapsack_problem/make_performance_plot.py
knapsack_problem/memory_test.png
knapsack_problem/mprofile_20190819094003.dat
knapsack_problem/performance.json
knapsack_problem/performance.py
knapsack_problem/ref_func.py
knapsack_problem/result.png
knapsack_problem/result2.png
knapsack_problem/results.md
knapsack_problem/tests.py
tree_sort/__init__.py
tree_sort/data.py
tree_sort/funcs.py
tree_sort/funcs.py.lprof
tree_sort/make_performance_plot.py
tree_sort/memory_test.png
tree_sort/mprofile_20190819154402.dat
tree_sort/performance.json
tree_sort/performance.py
tree_sort/result.png
tree_sort/results.md
tree_sort/tests.py
unpacking_flatten_lists/__init__.py
unpacking_flatten_lists/data.py
unpacking_flatten_lists/funcs.py
unpacking_flatten_lists/funcs.py.lprof
unpacking_flatten_lists/make_performance_plot.py
unpacking_flatten_lists/memory_test.png
unpacking_flatten_lists/mprofile_20190827164514.dat
unpacking_flatten_lists/performance.json
unpacking_flatten_lists/performance.py
unpacking_flatten_lists/result.png
unpacking_flatten_lists/result2.png
unpacking_flatten_lists/results.md
Intrst_algrms-0.7.2.dist-info/LICENSE.md
Intrst_algrms-0.7.2.dist-info/METADATA
Intrst_algrms-0.7.2.dist-info/WHEEL
Intrst_algrms-0.7.2.dist-info/top_level.txt
Intrst_algrms-0.7.2.dist-info/RECORD
