Metadata-Version: 2.1
Name: Intrst-algrms
Version: 0.7.2
Summary: https://intrst-algrms.readthedocs.io/en/latest/
Home-page: https://pypi.org/project/Intrst-algrms/
Author: Nikolai Vidov
Author-email: lastsal@mail.ru
License: MIT
Keywords: example documentation algorithms
Platform: any
Classifier: Development Status :: 5 - Production/Stable
Classifier: Environment :: Other Environment
Classifier: Intended Audience :: Developers
Classifier: License :: OSI Approved :: MIT License
Classifier: Operating System :: OS Independent
Classifier: Programming Language :: Python
Classifier: Programming Language :: Python :: 3.6
Classifier: Programming Language :: Python :: 3.7
Classifier: Topic :: Software Development :: Libraries :: Python Modules
Requires-Python: >=3.6
Requires-Dist: iteration-utilities
Requires-Dist: more-itertools
Provides-Extra: all
Requires-Dist: Sphinx ; extra == 'all'
Requires-Dist: memory-profiler ; extra == 'all'
Requires-Dist: matplotlib ; extra == 'all'
Provides-Extra: docs
Requires-Dist: Sphinx ; extra == 'docs'
Provides-Extra: tests
Requires-Dist: memory-profiler ; extra == 'tests'
Requires-Dist: matplotlib ; extra == 'tests'
